{
  "id": "advance-data-science/chap10",
  "title": "chap10",
  "description": "Chương 10: Phân rã giá trị suy biến (Singular Value Decomposition - SVD)",
  "source": "@site/linear-algebra/advance-data-science/chap10.md",
  "sourceDirName": "advance-data-science",
  "slug": "/advance-data-science/chap10",
  "permalink": "/linear-algebra/advance-data-science/chap10",
  "draft": false,
  "unlisted": false,
  "editUrl": "https://github.com/quadang21cen/quadang21cen.github.io/tree/main/linear-algebra/advance-data-science/chap10.md",
  "tags": [],
  "version": "current",
  "lastUpdatedBy": "Author",
  "lastUpdatedAt": 1539502055000,
  "sidebarPosition": 1,
  "frontMatter": {
    "sidebar_position": 1
  },
  "sidebar": "linearAlgebraSidebar",
  "previous": {
    "title": "Phần V: Các chủ đề nâng cao và Ứng dụng trong Khoa học dữ liệu",
    "permalink": "/linear-algebra/category/phần-v-các-chủ-đề-nâng-cao-và-ứng-dụng-trong-khoa-học-dữ-liệu"
  },
  "next": {
    "title": "Chương 9: Phân rã Ma trận và các Dạng chính tắc (Matrix Decompositions and Canonical Forms)",
    "permalink": "/linear-algebra/advance-data-science/chap9-matrix-decompositions-and-canonical-forms"
  }
}